setup.cfg
setup.py
resets/__init__.py
resets/manager.py
resets/trans.py
resets/wiki.py
resets.egg-info/PKG-INFO
resets.egg-info/SOURCES.txt
resets.egg-info/dependency_links.txt
resets.egg-info/requires.txt
resets.egg-info/top_level.txt