Metadata-Version: 2.1
Name: resets
Version: 0.0.3
Summary: Python module for writing websites.Two It 2022 (two-it.netlify.app API wrapper)
Home-page: https://github.com/TwoIt202/Resets
Download-URL: https://github.com/TwoIt202/Resets/raw/9f61338524c629ef2d70e7cb7f80a7bfb0d395c4/resets.zip
Author: two-it2022
Author-email: kodland.group@gmail.com
License: Apache License, Version 1.2, see LICENSE file
Classifier: License :: OSI Approved :: Apache Software License
Classifier: Operating System :: OS Independent
Classifier: Intended Audience :: End Users/Desktop
Classifier: Intended Audience :: Developers
Classifier: Programming Language :: Python
Classifier: Programming Language :: Python :: 3
Classifier: Programming Language :: Python :: 3.6
Classifier: Programming Language :: Python :: 3.7
Classifier: Programming Language :: Python :: 3.8
Classifier: Programming Language :: Python :: Implementation :: PyPy
Classifier: Programming Language :: Python :: Implementation :: CPython
